vcf_wiper/__init__.py
vcf_wiper/color_log_formatter.py
vcf_wiper/wiper.py
vcfwiper-2021.1.4.dist-info/LICENSE
vcfwiper-2021.1.4.dist-info/METADATA
vcfwiper-2021.1.4.dist-info/WHEEL
vcfwiper-2021.1.4.dist-info/entry_points.txt
vcfwiper-2021.1.4.dist-info/top_level.txt
vcfwiper-2021.1.4.dist-info/RECORD
