Metadata-Version: 2.1
Name: vcfwiper
Version: 2021.1.4
Summary: A package to wipe out uncompliant VCF files
Home-page: https://github.com/mazzalab/fastqwiper
Author: Tommaso Mazza
Author-email: bioinformatics@css-mendel.it
License: MIT
Project-URL: Source, https://github.com/mazzalab/vcfwiper
Project-URL: Tracker, https://github.com/mazzalab/vcfwiper/issues
Project-URL: Developmental plan, https://github.com/mazzalab/vcfwiper/projects
Keywords: genomics,ngs,fastq,bioinformatics
Platform: UNKNOWN
Classifier: Development Status :: 5 - Production/Stable
Classifier: Intended Audience :: Science/Research
Classifier: Programming Language :: Python :: 3.8
Classifier: License :: OSI Approved :: MIT License
Classifier: Operating System :: OS Independent
Requires-Python: <=3.9
Requires-Dist: setuptools
Requires-Dist: colorama (==0.4.4)
Requires-Dist: click (==7.1.2)
